x17_code/__init__.py
x17_lib_code-0.1.0.dist-info/METADATA
x17_lib_code-0.1.0.dist-info/WHEEL
x17_lib_code-0.1.0.dist-info/top_level.txt
x17_lib_code-0.1.0.dist-info/RECORD
